{
  "main": {
    "id": "5790572822a54bb9",
    "type": "split",
    "children": [
      {
        "id": "1327b1be5496bee0",
        "type": "tabs",
        "children": [
          {
            "id": "53a510708acaea20",
            "type": "leaf",
            "state": {
              "type": "markdown",
              "state": {
                "file": "Education/Ежедневник/2024/Май.md",
                "mode": "source",
                "source": false
              }
            }
          },
          {
            "id": "687bed99f48357d2",
            "type": "leaf",
            "state": {
              "type": "markdown",
              "state": {
                "file": "Daily/2024-05-31.md",
                "mode": "source",
                "source": false
              }
            }
          }
        ],
        "currentTab": 1
      }
    ],
    "direction": "vertical"
  },
  "left": {
    "id": "da26d5b6ff904504",
    "type": "split",
    "children": [
      {
        "id": "44ec76f45123143e",
        "type": "tabs",
        "children": [
          {
            "id": "11eab32ae7923cc7",
            "type": "leaf",
            "state": {
              "type": "file-explorer",
              "state": {
                "sortOrder": "alphabetical"
              }
            }
          },
          {
            "id": "355f3c48f883c337",
            "type": "leaf",
            "state": {
              "type": "search",
              "state": {
                "query": "",
                "matchingCase": false,
                "explainSearch": false,
                "collapseAll": false,
                "extraContext": false,
                "sortOrder": "alphabetical"
              }
            }
          },
          {
            "id": "be4f0a976da7d3a9",
            "type": "leaf",
            "state": {
              "type": "bookmarks",
              "state": {}
            }
          }
        ]
      }
    ],
    "direction": "horizontal",
    "width": 300
  },
  "right": {
    "id": "1c6bb1d880474ec2",
    "type": "split",
    "children": [
      {
        "id": "93c19fda9683f167",
        "type": "tabs",
        "children": [
          {
            "id": "f74e9e9abbc95195",
            "type": "leaf",
            "state": {
              "type": "backlink",
              "state": {
                "file": "Daily/2024-05-31.md",
                "collapseAll": false,
                "extraContext": false,
                "sortOrder": "alphabetical",
                "showSearch": false,
                "searchQuery": "",
                "backlinkCollapsed": false,
                "unlinkedCollapsed": true
              }
            }
          },
          {
            "id": "066e319820e34127",
            "type": "leaf",
            "state": {
              "type": "outgoing-link",
              "state": {
                "file": "Daily/2024-05-31.md",
                "linksCollapsed": false,
                "unlinkedCollapsed": true
              }
            }
          },
          {
            "id": "7cb411708e0d134a",
            "type": "leaf",
            "state": {
              "type": "tag",
              "state": {
                "sortOrder": "frequency",
                "useHierarchy": true
              }
            }
          },
          {
            "id": "e3e1d7b2ff32e293",
            "type": "leaf",
            "state": {
              "type": "outline",
              "state": {
                "file": "Daily/2024-05-31.md"
              }
            }
          },
          {
            "id": "81f675be26297bbe",
            "type": "leaf",
            "state": {
              "type": "calendar",
              "state": {}
            }
          }
        ]
      }
    ],
    "direction": "horizontal",
    "width": 300,
    "collapsed": true
  },
  "left-ribbon": {
    "hiddenItems": {
      "switcher:Меню быстрого перехода": false,
      "graph:Граф": false,
      "canvas:Создать новый холст": false,
      "daily-notes:Сегодняшняя заметка": false,
      "templates:Вставить шаблон": false,
      "command-palette:Открыть палитру команд": false
    }
  },
  "active": "687bed99f48357d2",
  "lastOpenFiles": [
    "Daily/2024-05-30.md",
    "Daily/2024-05-31.md",
    "Education/Ежедневник/2024/Май.md",
    "Education/Ежедневник/2024/Июнь.md",
    "Cache/Произведения для ЕГЭ по русскому языку.pdf",
    "Daily/2024-05-27.md",
    "Daily/2024-05-19.md",
    "Daily/2024-05-20.md",
    "Daily/2024-05-23.md",
    "Daily/2024-05-24.md",
    "Daily/2024-05-25.md",
    "Daily/2024-05-26.md",
    "Cache/Сочинение Webium 2024-05-26.pdf",
    "Cache/Сочинение Webium 2024-05-26 #2 3.pdf",
    "Cache/Сочинение Webium 2024-05-26 #2 2.pdf",
    "Cache/Сочинение Webium 2024-05-26 #2 1.pdf",
    "Cache/Сочинение Webium 2024-05-26 #2.pdf",
    "Projects/Engine/ExploreMate/Explore Mate.md",
    "2045-05-25.md",
    "Daily/2024-05-15.md",
    "Daily/2024-05-17.md",
    "Daily/2024-05-18.md",
    "Cache/Сочинение Webium 2024-05-24.pdf",
    "Daily/2024-05-22.md",
    "Education/Книги/2024/Художественная литература/Судьба человека.md",
    "Cache/Сочинение Webium 2024-05-23.pdf",
    "Finance/2024/Апрель.md",
    "Finance/2024/Май.md",
    "Education/Книги/2024/Научная литература",
    "Education/Книги/2024/Художественная литература",
    "Cache/Pasted image 20240518001727.png",
    "Templates/Finance Template.md",
    "Daily/2024-05-21.md",
    "Templates/Daily Template.md",
    "Daily/2024-05-13.md",
    "Daily/2024-05-14.md",
    "Daily/2024-05-16.md",
    "Без названия.canvas"
  ]
}